{
	"exit": {
		"description": "Exits the program."
	},
	"password": {
		"description": "Lets the user pick a password to protect its account or disable it."
	},
	"set": {
		"description": "Sets the value for a setting.",
		"options": {"-t": "THEME:light/dark"}
	},
	"delete": {
		"description": "Deletes the user's profile."
	},
	"new": {
		"description": "Creates a new body."
	},
	"info": {
		"description": "Shows the list of bodies.",
		"options": {"--all": ""}
	},
	"remove": {
		"description": "Removes a body by its name.",
		"options": {"-n#": "BODY_NAME"}
	},
	"clear": {
		"description": "Clears the list of bodies."
	},
	"reset": {
		"description": "Resets bodies' trajectories."
	},
	"simulate": {
		"description": "Enters the specified account environment.",
		"options": {"-n#": "STEPS_NUMBER", "-t#": "STEP_SIZE"}
	},
	"plot": {
		"description": "Plots the trajectories.",
		"options": {"--animated": ""}
	}
}
